uhttp_negotiate/__init__.py
uhttp_negotiate/__version__.py
uhttp_negotiate/main.py
uhttp_negotiate/py.typed
uhttp_negotiate-0.1.1.dist-info/LICENSE
uhttp_negotiate-0.1.1.dist-info/METADATA
uhttp_negotiate-0.1.1.dist-info/WHEEL
uhttp_negotiate-0.1.1.dist-info/top_level.txt
uhttp_negotiate-0.1.1.dist-info/RECORD
