Metadata-Version: 2.1
Name: uhttp-negotiate
Version: 0.1.1
Summary: Negotiate auth flow for uhttp over SSPI
Home-page: https://github.com/newvicx/uhttp_negotiate
Author: Chris Newville
Author-email: chrisnewville1396@gmail.com
License: MIT
Project-URL: Changelog, https://github.com/newvicx/uhttp_negotiate/blob/master/CHANGELOG.md
Project-URL: Source, https://github.com/newvicx/uhttp_negotiate
Classifier: Development Status :: 4 - Beta
Classifier: Environment :: Web Environment
Classifier: Intended Audience :: Developers
Classifier: License :: OSI Approved :: MIT License
Classifier: Operating System :: Microsoft :: Windows
Classifier: Topic :: Internet :: WWW/HTTP
Classifier: Programming Language :: Python :: 3
Classifier: Programming Language :: Python :: 3.8
Classifier: Programming Language :: Python :: 3.9
Classifier: Programming Language :: Python :: 3.10
Classifier: Programming Language :: Python :: 3 :: Only
Requires-Python: >=3.8
License-File: LICENSE
Requires-Dist: pywin32 (>=304)
Requires-Dist: uhttp (>=0.1.0)
